mammon/__init__.py
mammon/exceptions.py
mammon/host.py
mammon/policy.py
mammon/result.py
mammon/script.py
mammon-0.0.1.dist-info/DESCRIPTION.rst
mammon-0.0.1.dist-info/METADATA
mammon-0.0.1.dist-info/RECORD
mammon-0.0.1.dist-info/WHEEL
mammon-0.0.1.dist-info/metadata.json
mammon-0.0.1.dist-info/top_level.txt
